src/arbiter.v
// =============================================================================
// arbiter.v - Round-robin bus arbiter for 4 cache controllers
//
// Grants bus access to one core at a time. After each grant, priority rotates
// to the next core so no core can starve.
//
// Grant is held stable until the winning core drops its req bit (releases bus).
// One-hot encoding: grant[i] = 1 means core i currently owns the bus.
// grant_valid = OR of all grant bits, high when any core holds the bus.
// =============================================================================

module arbiter (
    input            clk,
    input            resetn,
    input      [3:0] req,        // one bit per core, high = wants bus
    output reg [3:0] grant,      // one-hot, which core has the bus
    output           grant_valid  // is anyone currently granted?
);

    assign grant_valid = |grant;

    // priority: which core gets checked first next arbitration round
    reg [1:0] priority;

    always @(posedge clk) begin
        if (!resetn) begin
            grant    <= 4'b0000;
            priority <= 2'd0;
        end else begin
            // Release grant when the granted core drops its req bit
            if (grant_valid && !(req & grant)) begin
                grant <= 4'b0000;
            end
            // If no one currently holds the bus, arbitrate.
            // Scan all four cores starting from priority, wrapping around.
            // Grant to the first one that has a request.
            // Rotate priority to (winner+1) after each grant so no core starves.
            else if (!grant_valid) begin
                if (req[(priority+0) % 4]) begin
                    grant    <= 4'b0001 << ((priority+0) % 4);
                    priority <= (priority+1) % 4;
                end
                else if (req[(priority+1) % 4]) begin
                    grant    <= 4'b0001 << ((priority+1) % 4);
                    priority <= (priority+2) % 4;
                end
                else if (req[(priority+2) % 4]) begin
                    grant    <= 4'b0001 << ((priority+2) % 4);
                    priority <= (priority+3) % 4;
                end
                else if (req[(priority+3) % 4]) begin
                    grant    <= 4'b0001 << ((priority+3) % 4);
                    priority <= (priority+4) % 4;
                end
            end
            // If grant_valid and req still asserted for winner, hold grant stable
        end
    end

endmodule

src/tb_arbiter.v
// =============================================================================
// tb_arbiter.v - Directed testbench for round-robin arbiter
//
// Resets between each test to get clean priority state (priority=0).
//
// Tests covered:
//   1. Single requester         - only core 2 requests, should get grant
//   2. Simultaneous requests    - cores 1,2,3 all request, verify round-robin
//   3. All four cores           - all request, verify full round-robin cycle
//   4. Late arrival             - core joins mid-sequence
// =============================================================================

`timescale 1ns/1ps

module tb_arbiter;

    reg        clk;
    reg        resetn;
    reg  [3:0] req;
    wire [3:0] grant;
    wire       grant_valid;

    initial clk = 0;
    always #5 clk = ~clk;

    arbiter dut (
        .clk         (clk),
        .resetn      (resetn),
        .req         (req),
        .grant       (grant),
        .grant_valid (grant_valid)
    );

    integer pass_count;
    integer fail_count;

    task check_grant;
        input [3:0] expected_grant;
        input [63:0] test_name;
        begin
            if (grant === expected_grant) begin
                $display("  [PASS] %s: grant=0b%04b", test_name, grant);
                pass_count = pass_count + 1;
            end else begin
                $display("  [FAIL] %s: got 0b%04b, expected 0b%04b",
                         test_name, grant, expected_grant);
                fail_count = fail_count + 1;
            end
        end
    endtask

    task wait_for_grant;
        integer timeout;
        begin
            timeout = 0;
            while (!grant_valid && timeout < 20) begin
                @(posedge clk);
                timeout = timeout + 1;
            end
            if (timeout >= 20)
                $display("  [TIMEOUT] waited too long for grant");
        end
    endtask

    task release_bus;
        begin
            req = req & ~grant;
            @(posedge clk);
            @(posedge clk);
        end
    endtask

    // Full reset - clears grant and priority back to 0
    task do_reset;
        begin
            req    = 4'b0000;
            resetn = 0;
            repeat(4) @(posedge clk);
            resetn = 1;
            repeat(2) @(posedge clk);
        end
    endtask

    initial begin
        $dumpfile("tb_arbiter.vcd");
        $dumpvars(0, tb_arbiter);

        pass_count = 0;
        fail_count = 0;

        // =====================================================================
        // Test 1: Single requester - core 2 only
        // Priority=0 after reset. Core 2 is only requester.
        // Expected: core 2 gets grant
        // =====================================================================
        $display("\n--- Test 1: Single requester (core 2) ---");
        do_reset;
        req = 4'b0100;
        wait_for_grant;
        @(posedge clk);
        check_grant(4'b0100, "single req core 2");
        release_bus;

        // =====================================================================
        // Test 2: Simultaneous requests from cores 1, 2, 3
        // Priority=0 after reset. Core 0 not requesting.
        // Expected order: core 1, core 2, core 3
        // =====================================================================
        $display("\n--- Test 2: Simultaneous requests (cores 1,2,3) ---");
        do_reset;
        req = 4'b1110;
        wait_for_grant;
        @(posedge clk);
        check_grant(4'b0010, "simultaneous: core 1 first");
        release_bus;

        wait_for_grant;
        @(posedge clk);
        check_grant(4'b0100, "simultaneous: core 2 second");
        release_bus;

        wait_for_grant;
        @(posedge clk);
        check_grant(4'b1000, "simultaneous: core 3 third");
        release_bus;

        // =====================================================================
        // Test 3: All four cores request simultaneously
        // Priority=0 after reset.
        // Expected order: 0, 1, 2, 3
        // =====================================================================
        $display("\n--- Test 3: All four cores request ---");
        do_reset;
        req = 4'b1111;
        wait_for_grant;
        @(posedge clk);
        check_grant(4'b0001, "all four: core 0 first");
        release_bus;

        wait_for_grant;
        @(posedge clk);
        check_grant(4'b0010, "all four: core 1 second");
        release_bus;

        wait_for_grant;
        @(posedge clk);
        check_grant(4'b0100, "all four: core 2 third");
        release_bus;

        wait_for_grant;
        @(posedge clk);
        check_grant(4'b1000, "all four: core 3 fourth");
        release_bus;

        // =====================================================================
        // Test 4: Late arrival
        // Priority=0 after reset. Core 0 requests alone, then core 3 joins.
        // Expected: core 0 wins first, then core 3
        // =====================================================================
        $display("\n--- Test 4: Late arrival ---");
        do_reset;
        req = 4'b0001;
        wait_for_grant;
        @(posedge clk);
        check_grant(4'b0001, "late arrival: core 0 first");
        req = req | 4'b1000;  // core 3 joins while core 0 has bus
        release_bus;

        wait_for_grant;
        @(posedge clk);
        check_grant(4'b1000, "late arrival: core 3 next");
        release_bus;

        // =====================================================================
        // Summary
        // =====================================================================
        $display("\n=================================================");
        $display("  Results: %0d passed, %0d failed", pass_count, fail_count);
        $display("=================================================\n");

        if (fail_count == 0)
            $display("ALL TESTS PASSED!\n");
        else
            $display("SOME TESTS FAILED - check output above\n");

        $finish;
    end

    initial begin
        #10000;
        $display("[TIMEOUT] simulation hung");
        $finish;
    end

endmodule

src/tb_arbiter.vcd
$date
	Tue Mar 24 15:48:21 2026
$end
$version
	Icarus Verilog
$end
$timescale
	1ps
$end
$scope module tb_arbiter $end
$var wire 1 ! grant_valid $end
$var wire 4 " grant [3:0] $end
$var reg 1 # clk $end
$var reg 4 $ req [3:0] $end
$var reg 1 % resetn $end
$var integer 32 & fail_count [31:0] $end
$var integer 32 ' pass_count [31:0] $end
$scope module dut $end
$var wire 1 # clk $end
$var wire 4 ( req [3:0] $end
$var wire 1 % resetn $end
$var wire 1 ! grant_valid $end
$var reg 4 ) grant [3:0] $end
$var reg 2 * priority [1:0] $end
$upscope $end
$scope task check_grant $end
$var reg 4 + expected_grant [3:0] $end
$var reg 64 , test_name [63:0] $end
$upscope $end
$scope task do_reset $end
$upscope $end
$scope task release_bus $end
$upscope $end
$scope task wait_for_grant $end
$var integer 32 - timeout [31:0] $end
$upscope $end
$upscope $end
$enddefinitions $end
#0
$dumpvars
bx -
bx ,
bx +
bx *
bx )
b0 (
b0 '
b0 &
0%
b0 $
0#
bx "
x!
$end
#5000
b0 *
0!
b0 "
b0 )
1#
#10000
0#
#15000
1#
#20000
0#
#25000
1#
#30000
0#
#35000
1%
1#
#40000
0#
#45000
1#
#50000
0#
#55000
b0 -
b100 $
b100 (
1#
#60000
0#
#65000
b11 *
1!
b100 "
b100 )
b1 -
1#
#70000
0#
#75000
b10 -
1#
#80000
0#
#85000
b0 $
b0 (
b1 '
b111000100100000011000110110111101110010011001010010000000110010 ,
b100 +
1#
#90000
0#
#95000
0!
b0 "
b0 )
1#
#100000
0#
#105000
0%
1#
#110000
0#
#115000
b0 *
1#
#120000
0#
#125000
1#
#130000
0#
#135000
1#
#140000
0#
#145000
1%
1#
#150000
0#
#155000
1#
#160000
0#
#165000
b0 -
b1110 $
b1110 (
1#
#170000
0#
#175000
b10 *
1!
b10 "
b10 )
b1 -
1#
#180000
0#
#185000
b10 -
1#
#190000
0#
#195000
b1100 $
b1100 (
b10 '
b10000000110001001000000110011001101001011100100111001101110100 ,
b10 +
1#
#200000
0#
#205000
0!
b0 "
b0 )
1#
#210000
0#
#215000
b11 *
1!
b100 "
b100 )
b0 -
1#
#220000
0#
#225000
b1 -
1#
#230000
0#
#235000
b1000 $
b1000 (
b11 '
b11001000100000011100110110010101100011011011110110111001100100 ,
b100 +
1#
#240000
0#
#245000
0!
b0 "
b0 )
1#
#250000
0#
#255000
b0 *
1!
b1000 "
b1000 )
b0 -
1#
#260000
0#
#265000
b1 -
1#
#270000
0#
#275000
b0 $
b0 (
b100 '
b10000000110011001000000111010001101000011010010111001001100100 ,
b1000 +
1#
#280000
0#
#285000
0!
b0 "
b0 )
1#
#290000
0#
#295000
0%
1#
#300000
0#
#305000
1#
#310000
0#
#315000
1#
#320000
0#
#325000
1#
#330000
0#
#335000
1%
1#
#340000
0#
#345000
1#
#350000
0#
#355000
b0 -
b1111 $
b1111 (
1#
#360000
0#
#365000
b1 *
1!
b1 "
b1 )
b1 -
1#
#370000
0#
#375000
b10 -
1#
#380000
0#
#385000
b1110 $
b1110 (
b101 '
b10000000110000001000000110011001101001011100100111001101110100 ,
b1 +
1#
#390000
0#
#395000
0!
b0 "
b0 )
1#
#400000
0#
#405000
b10 *
1!
b10 "
b10 )
b0 -
1#
#410000
0#
#415000
b1 -
1#
#420000
0#
#425000
b1100 $
b1100 (
b110 '
b11000100100000011100110110010101100011011011110110111001100100 ,
b10 +
1#
#430000
0#
#435000
0!
b0 "
b0 )
1#
#440000
0#
#445000
b11 *
1!
b100 "
b100 )
b0 -
1#
#450000
0#
#455000
b1 -
1#
#460000
0#
#465000
b1000 $
b1000 (
b111 '
b10000000110010001000000111010001101000011010010111001001100100 ,
b100 +
1#
#470000
0#
#475000
0!
b0 "
b0 )
1#
#480000
0#
#485000
b0 *
1!
b1000 "
b1000 )
b0 -
1#
#490000
0#
#495000
b1 -
1#
#500000
0#
#505000
b0 $
b0 (
b1000 '
b11001100100000011001100110111101110101011100100111010001101000 ,
b1000 +
1#
#510000
0#
#515000
0!
b0 "
b0 )
1#
#520000
0#
#525000
0%
1#
#530000
0#
#535000
1#
#540000
0#
#545000
1#
#550000
0#
#555000
1#
#560000
0#
#565000
1%
1#
#570000
0#
#575000
1#
#580000
0#
#585000
b0 -
b1 $
b1 (
1#
#590000
0#
#595000
b1 *
1!
b1 "
b1 )
b1 -
1#
#600000
0#
#605000
b10 -
1#
#610000
0#
#615000
b1000 $
b1000 (
b1001 '
b10000000110000001000000110011001101001011100100111001101110100 ,
b1 +
1#
#620000
0#
#625000
0!
b0 "
b0 )
1#
#630000
0#
#635000
b0 *
1!
b1000 "
b1000 )
b0 -
1#
#640000
0#
#645000
b1 -
1#
#650000
0#
#655000
b0 $
b0 (
b1010 '
b110010100100000001100110010000001101110011001010111100001110100 ,
b1000 +
1#
#660000
0#
#665000
0!
b0 "
b0 )
1#
