src/cache.v
module cache (
    input           clk,
    input           resetn,

    // Core-facing interface (connects to PicoRV32)
    // core_valid: core is requesting a memory transaction
    // core_ready: cache signals to core that transaction is complete
    // core_wstrb: byte-enable mask (0000 = read, else = write)
    input           core_valid,
    output reg      core_ready,
    input  [31:0]   core_addr,
    input  [31:0]   core_wdata,
    input  [3:0]    core_wstrb,
    output reg [31:0] core_rdata,

    // Memory-facing interface (connects to shared memory)
    // mem_valid: cache is requesting a memory transaction
    // mem_ready: memory signals to cache that transaction is complete
    // mem_wstrb: 0000 = read (fetch), 1111 = write (writeback)
    output reg          mem_valid,
    input               mem_ready,
    output reg [31:0]   mem_addr,
    output reg [31:0]   mem_wdata,
    output reg [3:0]    mem_wstrb,
    input      [31:0]   mem_rdata
);

    // -------------------------------------------------------------------------
    // Cache storage - 4 direct-mapped lines, one word each
    //   valid: is there anything stored here at all?
    //   dirty: has this line been written locally but not sent to memory yet?
    //   tag:   which memory address does this line belong to?
    //   data:  the actual cached word
    // -------------------------------------------------------------------------
    reg [31:0] data  [0:3];
    reg [27:0] tag   [0:3];
    reg        valid [0:3];
    reg        dirty [0:3];

    // -------------------------------------------------------------------------
    // Address breakdown
    // Every 32-bit address splits into three fields:
    //   [31:4] tag   (28 bits) - which memory block is this?
    //   [3:2]  index (2 bits)  - which of the 4 cache lines to look in
    //   [1:0]  byte offset     - ignored, we are word-addressed
    //
    // addr_tag/addr_index: from core_addr, used in IDLE to sample the request
    // latched_tag/latched_index: from latched_addr, stable across all cycles
    // -------------------------------------------------------------------------
    wire [27:0] addr_tag    = core_addr[31:4];
    wire [1:0]  addr_index  = core_addr[3:2];

    wire [27:0] latched_tag   = latched_addr[31:4];
    wire [1:0]  latched_index = latched_addr[3:2];

    // -------------------------------------------------------------------------
    // Hit detection
    // A hit requires both:
    //   1. The slot is occupied (valid bit set)
    //   2. The slot contains our address (tag matches)
    // Uses latched address since we check this after IDLE has captured request
    // -------------------------------------------------------------------------
    wire hit = valid[latched_index] && (tag[latched_index] == latched_tag);

    // -------------------------------------------------------------------------
    // State machine parameters
    // 3 bits needed to represent 5 states (2 bits only gives 4)
    // -------------------------------------------------------------------------
    localparam IDLE      = 3'd0;  // waiting for core request
    localparam COMPARE   = 3'd1;  // check tag and valid bit
    localparam WRITEBACK = 3'd2;  // flush dirty line to memory before eviction
    localparam FETCH     = 3'd3;  // load requested line from memory
    localparam DONE      = 3'd4;  // serve core, return to IDLE

    reg [2:0] state;

    // -------------------------------------------------------------------------
    // Latched request registers
    // PicoRV32 holds its output signals stable only until mem_ready goes high.
    // We may spend many cycles in WRITEBACK and FETCH before we are done.
    // So we capture the core's request in IDLE and hold it ourselves.
    // -------------------------------------------------------------------------
    reg [31:0] latched_addr;
    reg [31:0] latched_wdata;
    reg [3:0]  latched_wstrb;

    // -------------------------------------------------------------------------
    // Reset + state machine - MUST be one always block
    // Having two separate always blocks drive the same registers (state, valid,
    // dirty) creates multiple drivers which is undefined in Verilog.
    // Pattern: if (!resetn) handle reset, else run state machine.
    // -------------------------------------------------------------------------
    integer i;
    always @(posedge clk) begin
        if (!resetn) begin
            // Clear valid and dirty bits - cache starts empty.
            // tag and data don't need clearing - irrelevant when valid=0.
            for (i = 0; i < 4; i = i + 1) begin
                valid[i] <= 0;
                dirty[i] <= 0;
            end
            state      <= IDLE;
            core_ready <= 0;
            mem_valid  <= 0;
        end else begin
            case (state)

                // IDLE: do nothing until core makes a request.
                // When core_valid goes high, latch the request and move to COMPARE.
                // We latch here because core_addr/wdata/wstrb may change next cycle.
                IDLE: begin
                    core_ready <= 0;
                    mem_valid  <= 0;
                    // Guard with !core_ready: when DONE asserts core_ready=1 and
                    // transitions to IDLE in the same cycle, core_valid is still
                    // high (testbench hasn't deasserted yet). Without this guard
                    // we'd immediately re-latch the same request and corrupt state.
                    // core_ready=1 at this moment means we just came from DONE --
                    // skip this cycle and wait for core_valid to be re-asserted.
                    if (core_valid && !core_ready) begin
                        latched_addr  <= core_addr;
                        latched_wdata <= core_wdata;
                        latched_wstrb <= core_wstrb;
                        state         <= COMPARE;
                    end
                end

                // COMPARE: check whether the requested address is in the cache.
                // Hit:        go directly to DONE (serve core next cycle)
                // Clean miss: go to FETCH (slot is empty or stale, safe to overwrite)
                // Dirty miss: go to WRITEBACK first (must flush before overwriting)
                COMPARE: begin
                    if (hit) begin
                        state <= DONE;
                    end else begin
                        if (dirty[latched_index]) begin
                            state <= WRITEBACK;
                        end else begin
                            state <= FETCH;
                        end
                    end
                end

                // WRITEBACK: the slot we need is occupied by a dirty line.
                // We must send that dirty line to memory before we can use the slot.
                // The writeback address is reconstructed from the stored tag and index
                // (not latched_addr - that's the new address we want, not the old one).
                // Hold mem_valid high until mem_ready confirms the write completed.
                WRITEBACK: begin
                    mem_valid <= 1;
                    mem_addr  <= {tag[latched_index], latched_index, 2'b00};
                    mem_wdata <= data[latched_index];
                    mem_wstrb <= 4'b1111;  // full word write
                    if (mem_ready) begin
                        mem_valid <= 0;
                        state     <= FETCH;
                    end
                end

                // FETCH: load the requested line from memory into the cache slot.
                // mem_wstrb = 0000 signals a read to memory.
                // When mem_ready goes high, store the returned data, update the tag,
                // mark the line valid and clean, then proceed to DONE.
                FETCH: begin
                    mem_valid <= 1;
                    mem_addr  <= {latched_tag, latched_index, 2'b00};
                    mem_wstrb <= 4'b0000;  // read
                    if (mem_ready) begin
                        mem_valid            <= 0;
                        data[latched_index]  <= mem_rdata;
                        tag[latched_index]   <= latched_tag;
                        valid[latched_index] <= 1;
                        dirty[latched_index] <= 0;
                        state                <= DONE;
                    end
                end

                // DONE: the cache line is valid and current. Serve the core.
                // Read:  put the cached data on core_rdata
                // Write: update the cache line byte-by-byte using wstrb mask,
                //        set dirty bit (write-back policy: don't write to memory yet)
                // Either way, assert core_ready for one cycle then return to IDLE.
                DONE: begin
                    core_ready <= 1;
                    if (latched_wstrb == 4'b0000) begin
                        // Read
                        core_rdata <= data[latched_index];
                    end else begin
                        // Write - apply byte enables individually
                        if (latched_wstrb[0]) data[latched_index][ 7: 0] <= latched_wdata[ 7: 0];
                        if (latched_wstrb[1]) data[latched_index][15: 8] <= latched_wdata[15: 8];
                        if (latched_wstrb[2]) data[latched_index][23:16] <= latched_wdata[23:16];
                        if (latched_wstrb[3]) data[latched_index][31:24] <= latched_wdata[31:24];
                        dirty[latched_index] <= 1;
                    end
                    state <= IDLE;
                end

            endcase
        end
    end

endmodule

src/tb_cache.v
// =============================================================================
// tb_cache.v - Directed testbench for the cache module
//
// Tests covered:
//   1. Read miss (cold)       - first access to an address, cache is empty
//   2. Read hit               - second access to same address, should hit
//   3. Write hit              - write to a cached address, sets dirty bit
//   4. Read-back after write  - verify written data is returned correctly
//   5. Clean eviction         - access address that maps to same index,
//                               old line is clean so no writeback needed
//   6. Dirty eviction         - access address that maps to same index,
//                               old line is dirty so writeback must happen first
//   7. Write miss             - write to uncached address (write-allocate:
//                               fetch first, then write)
//   8. Byte-enable writes     - partial word writes using wstrb
//
// How direct-mapped conflict works in this cache:
//   index = addr[3:2], so addresses 0x00, 0x10, 0x20, 0x30... all map to
//   index 0. Accessing 0x10 after caching 0x00 forces an eviction of line 0.
//
// Memory model:
//   Simple array that responds in 1 cycle (mem_ready goes high the cycle
//   after mem_valid). Prints a message on every read and write so you can
//   see what the cache is doing to memory.
// =============================================================================

`timescale 1ns/1ps

module tb_cache;

    // -------------------------------------------------------------------------
    // Clock and reset
    // -------------------------------------------------------------------------
    reg clk;
    reg resetn;

    initial clk = 0;
    always #5 clk = ~clk;  // 100MHz clock, 10ns period

    // -------------------------------------------------------------------------
    // Cache DUT ports
    // -------------------------------------------------------------------------
    reg         core_valid;
    wire        core_ready;
    reg  [31:0] core_addr;
    reg  [31:0] core_wdata;
    reg  [3:0]  core_wstrb;
    wire [31:0] core_rdata;

    wire        mem_valid;
    reg         mem_ready;
    wire [31:0] mem_addr;
    wire [31:0] mem_wdata;
    wire [3:0]  mem_wstrb;
    reg  [31:0] mem_rdata;

    // -------------------------------------------------------------------------
    // Instantiate cache
    // -------------------------------------------------------------------------
    cache dut (
        .clk        (clk),
        .resetn     (resetn),
        .core_valid (core_valid),
        .core_ready (core_ready),
        .core_addr  (core_addr),
        .core_wdata (core_wdata),
        .core_wstrb (core_wstrb),
        .core_rdata (core_rdata),
        .mem_valid  (mem_valid),
        .mem_ready  (mem_ready),
        .mem_addr   (mem_addr),
        .mem_wdata  (mem_wdata),
        .mem_wstrb  (mem_wstrb),
        .mem_rdata  (mem_rdata)
    );

    // -------------------------------------------------------------------------
    // Simple memory model
    // 256 words (1KB). Responds to cache requests in 1 cycle.
    // mem_ready goes high the cycle after mem_valid, mimicking a real memory.
    // -------------------------------------------------------------------------
    reg [31:0] memory [0:255];
    integer    mem_idx;

    // Pre-load memory with known values so we can verify fetches
    initial begin
        for (mem_idx = 0; mem_idx < 256; mem_idx = mem_idx + 1)
            memory[mem_idx] = 32'hA000_0000 + mem_idx;  // e.g. 0xA0000005 at index 5
    end

    always @(posedge clk) begin
        mem_ready <= 0;
        if (mem_valid && !mem_ready) begin
            mem_ready <= 1;
            if (mem_wstrb == 4'b0000) begin
                // Read (fetch)
                mem_rdata <= memory[mem_addr >> 2];
                $display("  [MEM] READ  addr=0x%08h data=0x%08h", mem_addr, memory[mem_addr >> 2]);
            end else begin
                // Write (writeback)
                if (mem_wstrb[0]) memory[mem_addr >> 2][ 7: 0] <= mem_wdata[ 7: 0];
                if (mem_wstrb[1]) memory[mem_addr >> 2][15: 8] <= mem_wdata[15: 8];
                if (mem_wstrb[2]) memory[mem_addr >> 2][23:16] <= mem_wdata[23:16];
                if (mem_wstrb[3]) memory[mem_addr >> 2][31:24] <= mem_wdata[31:24];
                $display("  [MEM] WRITE addr=0x%08h data=0x%08h wstrb=%b", mem_addr, mem_wdata, mem_wstrb);
            end
        end
    end

    // -------------------------------------------------------------------------
    // Test infrastructure
    // -------------------------------------------------------------------------
    integer pass_count;
    integer fail_count;

    // Issue a read request to the cache and wait for core_ready.
    // Returns the data on core_rdata.
    task cache_read;
        input [31:0] addr;
        output [31:0] rdata;
        begin
            @(negedge clk);
            core_valid <= 1;
            core_addr  <= addr;
            core_wdata <= 32'b0;
            core_wstrb <= 4'b0000;  // 0000 = read
            @(posedge clk);
            while (!core_ready) @(posedge clk);
            rdata = core_rdata;
            @(negedge clk);
            core_valid <= 0;
            @(posedge clk);
        end
    endtask

    // Issue a write request to the cache and wait for core_ready.
    task cache_write;
        input [31:0] addr;
        input [31:0] wdata;
        input [3:0]  wstrb;
        begin
            @(negedge clk);
            core_valid <= 1;
            core_addr  <= addr;
            core_wdata <= wdata;
            core_wstrb <= wstrb;
            @(posedge clk);
            while (!core_ready) @(posedge clk);
            @(negedge clk);
            core_valid <= 0;
            @(posedge clk);
        end
    endtask

    // Check an expected value and print pass/fail
    task check;
        input [31:0] got;
        input [31:0] expected;
        input [127:0] test_name;
        begin
            if (got === expected) begin
                $display("  [PASS] %s: got 0x%08h", test_name, got);
                pass_count = pass_count + 1;
            end else begin
                $display("  [FAIL] %s: got 0x%08h, expected 0x%08h", test_name, got, expected);
                fail_count = fail_count + 1;
            end
        end
    endtask

    // -------------------------------------------------------------------------
    // Main test sequence
    // -------------------------------------------------------------------------
    reg [31:0] rdata;

    initial begin
        // Waveform dump - view with gtkwave tb_cache.vcd
        $dumpfile("tb_cache.vcd");
        $dumpvars(0, tb_cache);

        pass_count = 0;
        fail_count = 0;

        // Reset
        resetn     = 0;
        core_valid = 0;
        core_addr  = 0;
        core_wdata = 0;
        core_wstrb = 0;
        mem_ready  = 0;
        repeat(4) @(posedge clk);
        resetn = 1;
        repeat(2) @(posedge clk);

        // =====================================================================
        // Test 1: Read miss (cold cache)
        // Address 0x00 has never been accessed. Cache is empty.
        // Expected: cache goes IDLE→COMPARE→FETCH→DONE, fetches from memory.
        // Memory at word 0 was initialized to 0xA0000000.
        // =====================================================================
        $display("\n--- Test 1: Read miss (cold cache) ---");
        $display("  Accessing 0x00000000 for the first time");
        cache_read(32'h0000_0000, rdata);
        check(rdata, 32'hA000_0000, "cold read 0x00");

        // =====================================================================
        // Test 2: Read hit
        // Address 0x00 is now cached. Second access should hit immediately.
        // Expected: cache goes IDLE→COMPARE→DONE, no memory access.
        // =====================================================================
        $display("\n--- Test 2: Read hit ---");
        $display("  Accessing 0x00000000 again (should hit, no memory access)");
        cache_read(32'h0000_0000, rdata);
        check(rdata, 32'hA000_0000, "read hit 0x00");

        // =====================================================================
        // Test 3: Write hit
        // Address 0x00 is cached. Write to it - should update cache and set
        // dirty bit. No memory write yet (write-back policy).
        // =====================================================================
        $display("\n--- Test 3: Write hit ---");
        $display("  Writing 0xDEADBEEF to 0x00000000 (should hit, no memory write)");
        cache_write(32'h0000_0000, 32'hDEAD_BEEF, 4'b1111);

        // =====================================================================
        // Test 4: Read-back after write
        // Immediately read 0x00 back - should get 0xDEADBEEF from cache,
        // not 0xA0000000 from memory.
        // =====================================================================
        $display("\n--- Test 4: Read-back after write ---");
        cache_read(32'h0000_0000, rdata);
        check(rdata, 32'hDEAD_BEEF, "read-back after write");

        // =====================================================================
        // Test 5: Clean eviction
        // Address 0x10 maps to the same index as 0x00 (both have addr[3:2]=0).
        // Cache line 0 currently holds 0x00 (dirty from Test 3).
        // Wait - this is actually a dirty eviction. Let's first do a clean one.
        // Cache a new address at index 1 (0x04), then evict it cleanly with 0x14.
        // =====================================================================
        $display("\n--- Test 5: Clean eviction ---");
        $display("  First cache 0x00000004 (index 1, clean)");
        cache_read(32'h0000_0004, rdata);
        check(rdata, 32'hA000_0001, "cold read 0x04");

        $display("  Now access 0x00000014 (also index 1) - clean eviction of 0x04");
        cache_read(32'h0000_0014, rdata);
        // Memory at word 5 (0x14 >> 2 = 5) = 0xA0000005
        check(rdata, 32'hA000_0005, "clean eviction fetch 0x14");

        // =====================================================================
        // Test 6: Dirty eviction
        // Line 0 still holds 0x00 with dirty data (0xDEADBEEF from Test 3).
        // Access 0x10 which maps to same index 0.
        // Expected: cache writes back 0xDEADBEEF to addr 0x00, then fetches 0x10.
        // =====================================================================
        $display("\n--- Test 6: Dirty eviction ---");
        $display("  Accessing 0x00000010 (index 0) - should writeback 0x00 first");
        $display("  Expect to see [MEM] WRITE of 0xDEADBEEF then [MEM] READ of 0x10");
        cache_read(32'h0000_0010, rdata);
        // Memory at word 4 (0x10 >> 2 = 4) = 0xA0000004
        check(rdata, 32'hA000_0004, "dirty eviction fetch 0x10");
        // Verify writeback happened - memory[0] should now be 0xDEADBEEF
        check(memory[0], 32'hDEAD_BEEF, "writeback to memory[0]");

        // =====================================================================
        // Test 7: Write miss (write-allocate)
        // Write to 0x20 which is not cached.
        // Expected: fetch 0x20 from memory first, then apply the write.
        // After the write, reading back should return the written value.
        // =====================================================================
        $display("\n--- Test 7: Write miss (write-allocate) ---");
        $display("  Writing 0x12345678 to 0x00000020 (not cached)");
        $display("  Expect [MEM] READ of 0x20 (fetch), then no memory write yet");
        cache_write(32'h0000_0020, 32'h1234_5678, 4'b1111);
        cache_read(32'h0000_0020, rdata);
        check(rdata, 32'h1234_5678, "write-allocate read-back");

        // =====================================================================
        // Test 8: Byte-enable writes
        // Write only the low byte of a cached word using wstrb = 4'b0001.
        // The other three bytes should be unchanged.
        // =====================================================================
        $display("\n--- Test 8: Byte-enable (partial write) ---");
        // First cache 0x30
        cache_read(32'h0000_0030, rdata);
        $display("  Cached 0x30, value = 0x%08h", rdata);
        // Write only the lowest byte with 0xAB
        $display("  Writing 0x000000AB to 0x30 with wstrb=0001 (low byte only)");
        cache_write(32'h0000_0030, 32'h0000_00AB, 4'b0001);
        cache_read(32'h0000_0030, rdata);
        // Original value was 0xA000000C (word index 0x30>>2 = 12 = 0xC)
        // Low byte replaced with 0xAB: expect 0xA00000AB
        check(rdata, 32'hA000_00AB, "byte-enable low byte");

        // =====================================================================
        // Summary
        // =====================================================================
        $display("\n=================================================");
        $display("  Results: %0d passed, %0d failed", pass_count, fail_count);
        $display("=================================================\n");

        if (fail_count == 0)
            $display("ALL TESTS PASSED!\n");
        else
            $display("SOME TESTS FAILED - check output above\n");

        $finish;
    end

    // Timeout watchdog - if simulation runs over 10000 cycles something is hung
    initial begin
        #100000;
        $display("[TIMEOUT] Simulation exceeded 100000ns - possible hang in state machine");
        $finish;
    end

endmodule

src/tb_cache.vcd
$date
	Tue Mar 24 15:04:44 2026
$end
$version
	Icarus Verilog
$end
$timescale
	1ps
$end
$scope module tb_cache $end
$var wire 4 ! mem_wstrb [3:0] $end
$var wire 32 " mem_wdata [31:0] $end
$var wire 1 # mem_valid $end
$var wire 32 $ mem_addr [31:0] $end
$var wire 1 % core_ready $end
$var wire 32 & core_rdata [31:0] $end
$var reg 1 ' clk $end
$var reg 32 ( core_addr [31:0] $end
$var reg 1 ) core_valid $end
$var reg 32 * core_wdata [31:0] $end
$var reg 4 + core_wstrb [3:0] $end
$var reg 32 , mem_rdata [31:0] $end
$var reg 1 - mem_ready $end
$var reg 32 . rdata [31:0] $end
$var reg 1 / resetn $end
$var integer 32 0 fail_count [31:0] $end
$var integer 32 1 mem_idx [31:0] $end
$var integer 32 2 pass_count [31:0] $end
$scope module dut $end
$var wire 1 ' clk $end
$var wire 32 3 core_addr [31:0] $end
$var wire 1 ) core_valid $end
$var wire 32 4 core_wdata [31:0] $end
$var wire 4 5 core_wstrb [3:0] $end
$var wire 1 6 hit $end
$var wire 32 7 mem_rdata [31:0] $end
$var wire 1 - mem_ready $end
$var wire 1 / resetn $end
$var wire 28 8 latched_tag [27:0] $end
$var wire 2 9 latched_index [1:0] $end
$var wire 28 : addr_tag [27:0] $end
$var wire 2 ; addr_index [1:0] $end
$var reg 32 < core_rdata [31:0] $end
$var reg 1 % core_ready $end
$var reg 32 = latched_addr [31:0] $end
$var reg 32 > latched_wdata [31:0] $end
$var reg 4 ? latched_wstrb [3:0] $end
$var reg 32 @ mem_addr [31:0] $end
$var reg 1 # mem_valid $end
$var reg 32 A mem_wdata [31:0] $end
$var reg 4 B mem_wstrb [3:0] $end
$var reg 3 C state [2:0] $end
$var integer 32 D i [31:0] $end
$upscope $end
$scope task cache_read $end
$var reg 32 E addr [31:0] $end
$var reg 32 F rdata [31:0] $end
$upscope $end
$scope task cache_write $end
$var reg 32 G addr [31:0] $end
$var reg 32 H wdata [31:0] $end
$var reg 4 I wstrb [3:0] $end
$upscope $end
$scope task check $end
$var reg 32 J expected [31:0] $end
$var reg 32 K got [31:0] $end
$var reg 128 L test_name [127:0] $end
$upscope $end
$upscope $end
$enddefinitions $end
#0
$dumpvars
bx L
bx K
bx J
bx I
bx H
bx G
bx F
bx E
bx D
bx C
bx B
bx A
bx @
bx ?
bx >
bx =
bx <
b0 ;
b0 :
bx 9
bx 8
bx 7
x6
b0 5
b0 4
b0 3
b0 2
b100000000 1
b0 0
0/
bx .
0-
bx ,
b0 +
b0 *
0)
b0 (
0'
bx &
x%
bx $
x#
bx "
bx !
$end
#5000
0#
0%
b0 C
b100 D
1'
#10000
0'
#15000
b100 D
1'
#20000
0'
#25000
b100 D
1'
#30000
0'
#35000
1/
b100 D
1'
#40000
0'
#45000
1'
#50000
0'
#55000
b0 E
1'
#60000
1)
0'
#65000
06
b0 8
b0 9
b1 C
b0 ?
b0 >
b0 =
1'
#70000
0'
#75000
b11 C
1'
#80000
0'
#85000
b0 !
b0 B
b0 $
b0 @
1#
1'
#90000
0'
#95000
b10100000000000000000000000000000 ,
b10100000000000000000000000000000 7
1-
1'
#100000
0'
#105000
16
b100 C
0#
0-
1'
#110000
0'
#115000
b0 C
b10100000000000000000000000000000 &
b10100000000000000000000000000000 <
1%
1'
#120000
0'
#125000
0%
b10100000000000000000000000000000 F
1'
#130000
0)
0'
#135000
b1 2
b110001101101111011011000110010000100000011100100110010101100001011001000010000000110000011110000011000000110000 L
b10100000000000000000000000000000 J
b10100000000000000000000000000000 K
b10100000000000000000000000000000 .
1'
#140000
1)
0'
#145000
b1 C
1'
#150000
0'
#155000
b100 C
1'
#160000
0'
#165000
b0 C
1%
1'
#170000
0'
#175000
0%
1'
#180000
0)
0'
#185000
b1111 I
b11011110101011011011111011101111 H
b0 G
b10 2
b1110010011001010110000101100100001000000110100001101001011101000010000000110000011110000011000000110000 L
1'
#190000
b1111 +
b1111 5
b11011110101011011011111011101111 *
b11011110101011011011111011101111 4
1)
0'
#195000
b1 C
b1111 ?
b11011110101011011011111011101111 >
1'
#200000
0'
#205000
b100 C
1'
#210000
0'
#215000
b0 C
1%
1'
#220000
0'
#225000
0%
1'
#230000
0)
0'
#235000
1'
#240000
b0 +
b0 5
b0 *
b0 4
1)
0'
#245000
b1 C
b0 ?
b0 >
1'
#250000
0'
#255000
b100 C
1'
#260000
0'
#265000
b0 C
b11011110101011011011111011101111 &
b11011110101011011011111011101111 <
1%
1'
#270000
0'
#275000
0%
b11011110101011011011111011101111 F
1'
#280000
0)
0'
#285000
b100 E
b11 2
b1100010011000010110001101101011001000000110000101100110011101000110010101110010001000000111011101110010011010010111010001100101 L
b11011110101011011011111011101111 J
b11011110101011011011111011101111 K
b11011110101011011011111011101111 .
1'
#290000
b1 ;
b100 (
b100 3
1)
0'
#295000
06
b1 9
b1 C
b100 =
1'
#300000
0'
#305000
b11 C
1'
#310000
0'
#315000
b100 $
b100 @
1#
1'
#320000
0'
#325000
b10100000000000000000000000000001 ,
b10100000000000000000000000000001 7
1-
1'
#330000
0'
#335000
16
0-
b100 C
0#
1'
#340000
0'
#345000
b0 C
b10100000000000000000000000000001 &
b10100000000000000000000000000001 <
1%
1'
#350000
0'
#355000
0%
b10100000000000000000000000000001 F
1'
#360000
0)
0'
#365000
b10100 E
b100 2
b110001101101111011011000110010000100000011100100110010101100001011001000010000000110000011110000011000000110100 L
b10100000000000000000000000000001 J
b10100000000000000000000000000001 K
b10100000000000000000000000000001 .
1'
#370000
b1 :
b10100 (
b10100 3
1)
0'
#375000
06
b1 8
b1 C
b10100 =
1'
#380000
0'
#385000
b11 C
1'
#390000
0'
#395000
b10100 $
b10100 @
1#
1'
#400000
0'
#405000
b10100000000000000000000000000101 ,
b10100000000000000000000000000101 7
1-
1'
#410000
0'
#415000
16
0-
b100 C
0#
1'
#420000
0'
#425000
b0 C
b10100000000000000000000000000101 &
b10100000000000000000000000000101 <
1%
1'
#430000
0'
#435000
0%
b10100000000000000000000000000101 F
1'
#440000
0)
0'
#445000
b10000 E
b101 2
b1100011011101000110100101101111011011100010000001100110011001010111010001100011011010000010000000110000011110000011000100110100 L
b10100000000000000000000000000101 J
b10100000000000000000000000000101 K
b10100000000000000000000000000101 .
1'
#450000
b0 ;
b10000 (
b10000 3
1)
0'
#455000
06
b0 9
b1 C
b10000 =
1'
#460000
0'
#465000
b10 C
1'
#470000
0'
#475000
b1111 !
b1111 B
b11011110101011011011111011101111 "
b11011110101011011011111011101111 A
b0 $
b0 @
1#
1'
#480000
0'
#485000
1-
1'
#490000
0'
#495000
0-
b11 C
0#
1'
#500000
0'
#505000
b0 !
b0 B
b10000 $
b10000 @
1#
1'
#510000
0'
#515000
b10100000000000000000000000000100 ,
b10100000000000000000000000000100 7
1-
1'
#520000
0'
#525000
16
b100 C
0#
0-
1'
#530000
0'
#535000
b0 C
b10100000000000000000000000000100 &
b10100000000000000000000000000100 <
1%
1'
#540000
0'
#545000
0%
b10100000000000000000000000000100 F
1'
#550000
0)
0'
#555000
b10010001101000101011001111000 H
b100000 G
b111 2
b1100001011000110110101100100000011101000110111100100000011011010110010101101101011011110111001001111001010110110011000001011101 L
b11011110101011011011111011101111 J
b11011110101011011011111011101111 K
b10100000000000000000000000000100 .
1'
#560000
b10 :
b1111 +
b1111 5
b10010001101000101011001111000 *
b10010001101000101011001111000 4
b100000 (
b100000 3
1)
0'
#565000
06
b10 8
b1 C
b1111 ?
b10010001101000101011001111000 >
b100000 =
1'
#570000
0'
#575000
b11 C
1'
#580000
0'
#585000
b100000 $
b100000 @
1#
1'
#590000
0'
#595000
b10100000000000000000000000001000 ,
b10100000000000000000000000001000 7
1-
1'
#600000
0'
#605000
16
b100 C
0#
0-
1'
#610000
0'
#615000
b0 C
1%
1'
#620000
0'
#625000
0%
1'
#630000
0)
0'
#635000
b100000 E
1'
#640000
b0 +
b0 5
b0 *
b0 4
1)
0'
#645000
b1 C
b0 ?
b0 >
1'
#650000
0'
#655000
b100 C
1'
#660000
0'
#665000
b0 C
b10010001101000101011001111000 &
b10010001101000101011001111000 <
1%
1'
#670000
0'
#675000
0%
b10010001101000101011001111000 F
1'
#680000
0)
0'
#685000
b110000 E
b1000 2
b1101100011011110110001101100001011101000110010100100000011100100110010101100001011001000010110101100010011000010110001101101011 L
b10010001101000101011001111000 J
b10010001101000101011001111000 K
b10010001101000101011001111000 .
1'
#690000
b11 :
b110000 (
b110000 3
1)
0'
#695000
06
b11 8
b1 C
b110000 =
1'
#700000
0'
#705000
b10 C
1'
#710000
0'
#715000
b1111 !
b1111 B
b10010001101000101011001111000 "
b10010001101000101011001111000 A
1#
1'
#720000
0'
#725000
1-
1'
#730000
0'
#735000
0-
b11 C
0#
1'
#740000
0'
#745000
b0 !
b0 B
b110000 $
b110000 @
1#
1'
#750000
0'
#755000
b10100000000000000000000000001100 ,
b10100000000000000000000000001100 7
1-
1'
#760000
0'
#765000
16
b100 C
0#
0-
1'
#770000
0'
#775000
b0 C
b10100000000000000000000000001100 &
b10100000000000000000000000001100 <
1%
1'
#780000
0'
#785000
0%
b10100000000000000000000000001100 F
1'
#790000
0)
0'
#795000
b1 I
b10101011 H
b110000 G
b10100000000000000000000000001100 .
1'
#800000
b1 +
b1 5
b10101011 *
b10101011 4
1)
0'
#805000
b1 C
b1 ?
b10101011 >
1'
#810000
0'
#815000
b100 C
1'
#820000
0'
#825000
b0 C
1%
1'
#830000
0'
#835000
0%
1'
#840000
0)
0'
#845000
1'
#850000
b0 +
b0 5
b0 *
b0 4
1)
0'
#855000
b1 C
b0 ?
b0 >
1'
#860000
0'
#865000
b100 C
1'
#870000
0'
#875000
b0 C
b10100000000000000000000010101011 &
b10100000000000000000000010101011 <
1%
1'
#880000
0'
#885000
0%
b10100000000000000000000010101011 F
1'
#890000
0)
0'
#895000
b1001 2
b101101011001010110111001100001011000100110110001100101001000000110110001101111011101110010000001100010011110010111010001100101 L
b10100000000000000000000010101011 J
b10100000000000000000000010101011 K
b10100000000000000000000010101011 .
1'
